[
  {
    "fields": [
      {
        "name": "id",
        "type": "number",
        "title": "ID"
      },
      {
        "name": "title",
        "type": "string"
      },
      {
        "options": {
          "source": "title",
          "maxLength": 96
        },
        "validation": [
          {
            "rules": [
              {
                "flag": "custom"
              },
              {
                "flag": "presence",
                "constraint": "required"
              }
            ],
            "level": "error"
          }
        ],
        "name": "slug",
        "type": "slug"
      },
      {
        "name": "category",
        "type": "string"
      },
      {
        "options": {
          "hotspot": true
        },
        "name": "image",
        "type": "image"
      },
      {
        "description": "Grid position (1-16)",
        "name": "pos",
        "type": "number",
        "title": "Position"
      },
      {
        "name": "description",
        "type": "text"
      },
      {
        "name": "year",
        "type": "string"
      }
    ],
    "name": "project",
    "type": "document"
  },
  {
    "fields": [
      {
        "description": "URL friendly ID (e.g., sketch, printing)",
        "name": "id",
        "type": "string",
        "title": "ID"
      },
      {
        "name": "title",
        "type": "string"
      },
      {
        "name": "description",
        "type": "text"
      },
      {
        "options": {
          "hotspot": true
        },
        "name": "image",
        "type": "image"
      }
    ],
    "name": "category",
    "type": "document"
  }
]